fortunetelleracs1029/__init__.py
fortunetelleracs1029/__main__.py
fortunetelleracs1029/fortuneteller.py
fortunetelleracs1029-1.0.0.dist-info/LICENSE
fortunetelleracs1029-1.0.0.dist-info/METADATA
fortunetelleracs1029-1.0.0.dist-info/WHEEL
fortunetelleracs1029-1.0.0.dist-info/entry_points.txt
fortunetelleracs1029-1.0.0.dist-info/top_level.txt
fortunetelleracs1029-1.0.0.dist-info/RECORD
