Metadata-Version: 2.1
Name: fortunetelleracs1029
Version: 1.0.0
Summary: A fortune teller package, built with build using setuptools, uploaded to PyPI using twine, and distributed via pip.
Author-email: Andrei Stoica <andreicstoica@icloud.com>, Brandon Chen <bc2982@nyu.edu>, Charlie Xiang <yx2017@nyu.edu>, Sanjaya Bhatta <sb7677@nyu.edu>
License: GNU GENERAL PUBLIC LICENSE
Project-URL: Homepage, https://github.com/software-students-fall2022/python-package-exercise-project-3-team-16
Project-URL: Repository, https://github.com/software-students-fall2022/python-package-exercise-project-3-team-16.git
Project-URL: Bug Tracker, https://github.com/software-students-fall2022/python-package-exercise-project-3-team-16/issues
Keywords: python,package,build,fortune,teller,fortune-teller
Classifier: Programming Language :: Python :: 3
Classifier: Intended Audience :: Education
Classifier: License :: OSI Approved :: GNU General Public License v3 (GPLv3)
Classifier: Operating System :: OS Independent
Requires-Python: >=3.7
License-File: LICENSE
Provides-Extra: dev
Requires-Dist: pytest ; extra == 'dev'
